mofsyncondition/__init__.py
mofsyncondition/conditions/__init__.py
mofsyncondition/conditions/chemical_entity_regex.py
mofsyncondition/conditions/conditions_extraction.py
mofsyncondition/conditions/curate_linker_name.py
mofsyncondition/conditions/modified_regex_extract.py
mofsyncondition/conditions/organic_reagents_from_iupac_name.py
mofsyncondition/doc/__init__.py
mofsyncondition/doc/convert_html_to_text.py
mofsyncondition/doc/doc_parser.py
mofsyncondition/evaluation/average_result.py
mofsyncondition/evaluation/confusion-matrix_DT-CV.png
mofsyncondition/evaluation/confusion-matrix_DT-tfv.png
mofsyncondition/evaluation/confusion-matrix_LR-CV.png
mofsyncondition/evaluation/confusion-matrix_LR-tfv.png
mofsyncondition/evaluation/confusion-matrix_NB-CV.png
mofsyncondition/evaluation/confusion-matrix_NB-tfv.png
mofsyncondition/evaluation/confusion-matrix_NN-CV.png
mofsyncondition/evaluation/confusion-matrix_NN-tfv.png
mofsyncondition/evaluation/confusion-matrix_RF-CV.png
mofsyncondition/evaluation/confusion-matrix_RF-tfv.png
mofsyncondition/evaluation/confusion-matrix_SVM-CV.png
mofsyncondition/evaluation/confusion-matrix_SVM-tfv.png
mofsyncondition/evaluation/paragraph_model_evaluator.txt
mofsyncondition/io/__init__.py
mofsyncondition/io/filetyper.py
mofsyncondition/io/iupac_to_cheminfo.py
mofsyncondition/io/journal_api.py
mofsyncondition/models/__init__.py
mofsyncondition/models/ml_models/DT_CV_model.pkl
mofsyncondition/models/ml_models/DT_tfv_model.pkl
mofsyncondition/models/ml_models/LR_CV_model.pkl
mofsyncondition/models/ml_models/LR_tfv_model.pkl
mofsyncondition/models/ml_models/NB_CV_model.pkl
mofsyncondition/models/ml_models/NB_tfv_model.pkl
mofsyncondition/models/ml_models/RF_CV_model.pkl
mofsyncondition/models/ml_models/RF_tfv_model.pkl
mofsyncondition/models/ml_models/SVM_CV_model.pkl
mofsyncondition/models/ml_models/SVM_tfv_model.pkl
mofsyncondition/models/vectorizers/DT_CV.pkl
mofsyncondition/models/vectorizers/DT_tfv.pkl
mofsyncondition-0.1.1.dist-info/METADATA
mofsyncondition-0.1.1.dist-info/WHEEL
mofsyncondition-0.1.1.dist-info/licenses/LICENSE
mofsyncondition-0.1.1.dist-info/RECORD
