Metadata-Version: 2.4
Name: mofsyncondition
Version: 0.1.1
Summary: A python too for extracting synthesis condition of MOFs directly from journal articles in any file format (html, xml and pdf
License: MIT
License-File: LICENSE
Author: Dinga Wonanke
Author-email: dak52@uclive.ac.nz
Requires-Python: >=3.10,<3.14
Classifier: License :: OSI Approved :: MIT License
Classifier: Programming Language :: Python :: 3
Classifier: Programming Language :: Python :: 3.10
Classifier: Programming Language :: Python :: 3.11
Classifier: Programming Language :: Python :: 3.12
Classifier: Programming Language :: Python :: 3.13
Requires-Dist: ase (>=3.26.0,<4.0.0)
Requires-Dist: beautifulsoup4 (>=4.14.3,<5.0.0)
Requires-Dist: cirpy (>=1.0.2,<2.0.0)
Requires-Dist: en-chem-ner (>=0.1.0,<0.2.0)
Requires-Dist: inscriptis (>=2.7.0,<3.0.0)
Requires-Dist: matplotlib (>=3.10.8,<4.0.0)
Requires-Dist: nltk (>=3.9.2,<4.0.0)
Requires-Dist: numpy (<2)
Requires-Dist: pint (==0.24)
Requires-Dist: pubchempy (>=1.0.5,<2.0.0)
Requires-Dist: pymatgen (==2025.10.7)
Requires-Dist: pymupdf (>=1.26.7,<2.0.0)
Requires-Dist: pypdf2 (>=3.0.1,<4.0.0)
Requires-Dist: pytest (>=9.0.2,<10.0.0)
Requires-Dist: requests (>=2.32.5,<3.0.0)
Requires-Dist: scikit-learn (==1.3.0)
Requires-Dist: scyjava (>=1.12.1,<2.0.0)
Requires-Dist: selenium (>=4.39.0,<5.0.0)
Requires-Dist: sentence-transformers (>=5.2.0,<6.0.0)
Requires-Dist: spacy (>=3.7.2,<3.8.0)
Requires-Dist: torch (==2.2.2)
